odoo10_addon_test_base_import_async-10.0.1.0.0.99.dev2-py2.7-nspkg.pth
odoo/addons/test_base_import_async/__init__.py
odoo/addons/test_base_import_async/__manifest__.py
odoo/addons/test_base_import_async/static/description/icon.png
odoo/addons/test_base_import_async/tests/__init__.py
odoo/addons/test_base_import_async/tests/account.move.csv
odoo/addons/test_base_import_async/tests/data.xml
odoo/addons/test_base_import_async/tests/test_base_import_async.py
odoo10_addon_test_base_import_async-10.0.1.0.0.99.dev2.dist-info/METADATA
odoo10_addon_test_base_import_async-10.0.1.0.0.99.dev2.dist-info/RECORD
odoo10_addon_test_base_import_async-10.0.1.0.0.99.dev2.dist-info/WHEEL
odoo10_addon_test_base_import_async-10.0.1.0.0.99.dev2.dist-info/namespace_packages.txt
odoo10_addon_test_base_import_async-10.0.1.0.0.99.dev2.dist-info/top_level.txt
